mapmatching/__init__.py
mapmatching/geo.py
mapmatching/geojson.py
mapmatching/main.py
mapmatching/match.py
mapmatching/task.py
mapmatching/version.txt
mapmatching/lua/__init__.py
mapmatching/lua/scripts/a_star.lua
mapmatching/lua/scripts/del_redis_keys.lua
mapmatching/lua/scripts/list_scripts.lua
mapmatching/lua/scripts/max_distance.lua
mapmatching/lua/scripts/nodes_from_way.lua
mapmatching/lua/scripts/project_point.lua
mapmatching/lua/scripts/search.lua
mapmatching/lua/scripts/street_names_from_point.lua
mapmatching/lua/scripts/ways_from_gps.lua
mapmatching/lua/scripts/ways_from_transition.lua
mapmatching/overpass/streets.overpassql
mapmatching-0.1.5.dist-info/LICENSE.txt
mapmatching-0.1.5.dist-info/METADATA
mapmatching-0.1.5.dist-info/WHEEL
mapmatching-0.1.5.dist-info/entry_points.txt
mapmatching-0.1.5.dist-info/top_level.txt
mapmatching-0.1.5.dist-info/RECORD
